deepparse/__init__.py
deepparse/bpemb_url_bug_fix.py
deepparse/download_tools.py
deepparse/validations.py
deepparse/version.py
deepparse/weights_tools.py
deepparse/cli/__init__.py
deepparse/cli/download_model.py
deepparse/cli/download_models.py
deepparse/cli/parse.py
deepparse/cli/parser_arguments_adder.py
deepparse/cli/retrain.py
deepparse/cli/test.py
deepparse/cli/tools.py
deepparse/comparer/__init__.py
deepparse/comparer/addresses_comparer.py
deepparse/comparer/formatted_compared_addresses.py
deepparse/comparer/formatted_compared_addresses_raw.py
deepparse/comparer/formatted_compared_addresses_tags.py
deepparse/converter/__init__.py
deepparse/converter/data_padder.py
deepparse/converter/data_processor.py
deepparse/converter/data_processor_factory.py
deepparse/converter/target_converter.py
deepparse/data_validation/__init__.py
deepparse/data_validation/data_validation.py
deepparse/dataset_container/__init__.py
deepparse/dataset_container/dataset_container.py
deepparse/dataset_container/tools.py
deepparse/embeddings_models/__init__.py
deepparse/embeddings_models/bpemb_embeddings_model.py
deepparse/embeddings_models/embeddings_model.py
deepparse/embeddings_models/embeddings_model_factory.py
deepparse/embeddings_models/fasttext_embeddings_model.py
deepparse/embeddings_models/magnitude_embeddings_model.py
deepparse/errors/__init__.py
deepparse/errors/data_error.py
deepparse/errors/model_error.py
deepparse/errors/server_error.py
deepparse/metrics/__init__.py
deepparse/metrics/accuracy.py
deepparse/metrics/nll_loss.py
deepparse/network/__init__.py
deepparse/network/bpemb_seq2seq.py
deepparse/network/decoder.py
deepparse/network/embedding_network.py
deepparse/network/encoder.py
deepparse/network/fasttext_seq2seq.py
deepparse/network/model_factory.py
deepparse/network/model_loader.py
deepparse/network/seq2seq.py
deepparse/parser/__init__.py
deepparse/parser/address_parser.py
deepparse/parser/capturing.py
deepparse/parser/formatted_parsed_address.py
deepparse-0.9.14.dist-info/LICENSE
deepparse-0.9.14.dist-info/METADATA
deepparse-0.9.14.dist-info/WHEEL
deepparse-0.9.14.dist-info/entry_points.txt
deepparse-0.9.14.dist-info/top_level.txt
deepparse-0.9.14.dist-info/RECORD
