Metadata-Version: 2.1
Name: deepparse
Version: 0.9.14
Summary: A library for parsing multinational street addresses using deep learning.
Home-page: https://deepparse.org/
Download-URL: https://github.com/GRAAL-Research/deepparse/archive/v0.9.14.zip
Author: Marouane Yassine, David Beauchemin
Author-email: marouane.yassine.1@ulaval.ca, david.beauchemin.5@ulaval.ca
License: LGPLv3
Classifier: Development Status :: 5 - Production/Stable
Classifier: Intended Audience :: Developers
Classifier: Intended Audience :: Education
Classifier: Intended Audience :: Science/Research
Classifier: License :: OSI Approved :: GNU Lesser General Public License v3 (LGPLv3)
Classifier: Programming Language :: Python :: 3
Classifier: Programming Language :: Python :: 3.8
Classifier: Programming Language :: Python :: 3.9
Classifier: Programming Language :: Python :: 3.10
Classifier: Programming Language :: Python :: 3.11
Classifier: Topic :: Software Development :: Libraries
Classifier: Topic :: Software Development :: Libraries :: Python Modules
Classifier: Topic :: Scientific/Engineering
Classifier: Topic :: Scientific/Engineering :: Artificial Intelligence
Requires-Python: >=3.8
License-File: LICENSE
Requires-Dist: numpy<2.0.0
Requires-Dist: torch
Requires-Dist: bpemb
Requires-Dist: scipy
Requires-Dist: gensim>=4.3.3
Requires-Dist: requests
Requires-Dist: fasttext-wheel
Requires-Dist: pymagnitude-light
Requires-Dist: poutyne
Requires-Dist: pandas
Requires-Dist: urllib3
Requires-Dist: cloudpathlib[azure,gs,s3]
Requires-Dist: transformers
Requires-Dist: huggingface-hub
Provides-Extra: all
Requires-Dist: colorama; extra == "all"
Requires-Dist: fastapi[all]>=0.109.1; extra == "all"
Requires-Dist: uvicorn==0.22.0; extra == "all"
Requires-Dist: sentry-sdk[fastapi]>=2.0.0; extra == "all"
Requires-Dist: python-decouple==3.8; extra == "all"
Requires-Dist: black; extra == "all"
Requires-Dist: pylint; extra == "all"
Requires-Dist: pylint-django[with_django]==2.5.3; extra == "all"
Requires-Dist: pre-commit==3.3.3; extra == "all"
Requires-Dist: pycountry==22.3.5; extra == "all"
Requires-Dist: pytest; extra == "all"
Requires-Dist: pytest-asyncio; extra == "all"
Requires-Dist: pytest-cov; extra == "all"
Requires-Dist: pytest-env; extra == "all"
Requires-Dist: pytest-mock; extra == "all"
Requires-Dist: pytest-xdist[psutil]; extra == "all"
Requires-Dist: tensorboard==2.13.0; extra == "all"
Requires-Dist: sphinx==6.2.1; extra == "all"
Requires-Dist: sphinx-rtd-theme==1.2.2; extra == "all"
Provides-Extra: app
Requires-Dist: fastapi[all]>=0.109.1; extra == "app"
Requires-Dist: uvicorn==0.22.0; extra == "app"
Requires-Dist: sentry-sdk[fastapi]>=2.0.0; extra == "app"
Requires-Dist: python-decouple==3.8; extra == "app"
Provides-Extra: colorama
Requires-Dist: colorama; extra == "colorama"
